{
  "$schema": "https://ui.shadcn.com/schema/registry-item.json",
  "name": "diamond-demo",
  "type": "registry:example",
  "registryDependencies": [
    "diamond"
  ],
  "files": [
    {
      "path": "registry/default/examples/diamond-demo.tsx",
      "content": "import { Diamond } from \"@/registry/default/ui/diamond\"\n\nexport default function DiamondDemo() {\n  return (\n    <div className=\"w-full space-y-8 p-4\">\n      <div className=\"border-grid relative h-32 w-full border\">\n        <Diamond top left />\n        <Diamond top right />\n        <Diamond bottom left />\n        <Diamond bottom right />\n      </div>\n    </div>\n  )\n}\n",
      "type": "registry:example"
    }
  ]
}